oslo_db/__init__.py
oslo_db/_i18n.py
oslo_db/api.py
oslo_db/exception.py
oslo_db/options.py
oslo_db/warning.py
oslo_db/locale/en_GB/LC_MESSAGES/oslo_db.po
oslo_db/locale/es/LC_MESSAGES/oslo_db.po
oslo_db/locale/fr/LC_MESSAGES/oslo_db.po
oslo_db/sqlalchemy/__init__.py
oslo_db/sqlalchemy/asyncio_facade.py
oslo_db/sqlalchemy/enginefacade.py
oslo_db/sqlalchemy/engines.py
oslo_db/sqlalchemy/exc_filters.py
oslo_db/sqlalchemy/models.py
oslo_db/sqlalchemy/orm.py
oslo_db/sqlalchemy/provision.py
oslo_db/sqlalchemy/session.py
oslo_db/sqlalchemy/test_base.py
oslo_db/sqlalchemy/test_fixtures.py
oslo_db/sqlalchemy/test_migrations.py
oslo_db/sqlalchemy/types.py
oslo_db/sqlalchemy/update_match.py
oslo_db/sqlalchemy/utils.py
oslo_db/sqlalchemy/migration_cli/README.rst
oslo_db/sqlalchemy/migration_cli/__init__.py
oslo_db/sqlalchemy/migration_cli/ext_alembic.py
oslo_db/sqlalchemy/migration_cli/ext_base.py
oslo_db/sqlalchemy/migration_cli/manager.py
oslo_db/tests/__init__.py
oslo_db/tests/base.py
oslo_db/tests/fixtures.py
oslo_db/tests/test_api.py
oslo_db/tests/utils.py
oslo_db/tests/sqlalchemy/__init__.py
oslo_db/tests/sqlalchemy/base.py
oslo_db/tests/sqlalchemy/test_asyncio_facade.py
oslo_db/tests/sqlalchemy/test_enginefacade.py
oslo_db/tests/sqlalchemy/test_exc_filters.py
oslo_db/tests/sqlalchemy/test_fixtures.py
oslo_db/tests/sqlalchemy/test_migrate_cli.py
oslo_db/tests/sqlalchemy/test_migrations.py
oslo_db/tests/sqlalchemy/test_models.py
oslo_db/tests/sqlalchemy/test_options.py
oslo_db/tests/sqlalchemy/test_provision.py
oslo_db/tests/sqlalchemy/test_sqlalchemy.py
oslo_db/tests/sqlalchemy/test_types.py
oslo_db/tests/sqlalchemy/test_update_match.py
oslo_db/tests/sqlalchemy/test_utils.py
oslo_db-18.0.0.dist-info/licenses/AUTHORS
oslo_db-18.0.0.dist-info/licenses/LICENSE
oslo_db-18.0.0.dist-info/METADATA
oslo_db-18.0.0.dist-info/WHEEL
oslo_db-18.0.0.dist-info/entry_points.txt
oslo_db-18.0.0.dist-info/pbr.json
oslo_db-18.0.0.dist-info/top_level.txt
oslo_db-18.0.0.dist-info/RECORD
